excelerator/__init__.py
excelerator/exceptions.py
excelerator/normalize.py
excelerator/main/excel_interface.py
excelerator/main/fieldparser.py
excelerator/main/headers.py
excelerator/main/tableparser.py
excelerator/main/worksheetparser.py
EXCELerator-0.8.dist-info/WHEEL
EXCELerator-0.8.dist-info/METADATA
EXCELerator-0.8.dist-info/RECORD
